codo/__init__.py
codo/__main__.py
codo/core.py
codo/engine.py
codo/mongo.py
codo-0.1.0.dist-info/LICENSE
codo-0.1.0.dist-info/METADATA
codo-0.1.0.dist-info/WHEEL
codo-0.1.0.dist-info/RECORD
